postnord_api/__init__.py
postnord_api/postnord.py
postnord_api-0.0.1.dist-info/LICENSE
postnord_api-0.0.1.dist-info/METADATA
postnord_api-0.0.1.dist-info/WHEEL
postnord_api-0.0.1.dist-info/RECORD
