Metadata-Version: 2.1
Name: postnord_api
Version: 0.0.1
Summary: A python API wrapper for Postnord tracking
Author: dunderrrrrr
Author-email: emil.bjorkroth@gmail.com
Requires-Python: >=3.10,<4.0
Classifier: Programming Language :: Python :: 3
Classifier: Programming Language :: Python :: 3.10
Classifier: Programming Language :: Python :: 3.11
Classifier: Programming Language :: Python :: 3.12
Requires-Dist: httpx (>=0.28.1,<0.29.0)
Requires-Dist: pre-commit (>=4.1.0,<5.0.0)
Requires-Dist: pytest (>=8.3.4,<9.0.0)
Requires-Dist: respx (>=0.22.0,<0.23.0)
Requires-Dist: ruff (>=0.9.6,<0.10.0)
